{
  "CommunicationBusinessRules": [
    {
      "BusinessDimensionValues": {
        "BusinessProviderCode": "OFFIC",
        "BusinessUnitCode": "NT"
      },
      "Actions": [
        {
          "Channel": "Email",
          "TemplateId": "3XIE9A"
        }
      ]
    },
    {
      "BusinessDimensionValues": {
        "BusinessProviderCode": "QUAERAT_N",
        "BusinessUnitCode": "NT"
      },
      "Actions": [
        {
          "Channel": "Email",
          "TemplateId": "W5S1WT"
        }
      ]
    },
    {
      "BusinessDimensionValues": {
        "BusinessProviderCode": "QUAERAT_",
        "BusinessUnitCode": "NT"
      },
      "Actions": [
        {
          "Channel": "Email",
          "TemplateId": "HJYML3"
        }
      ]
    },
    {
      "BusinessDimensionValues": {
        "BusinessProviderCode": "EARUM_MOLES",
        "BusinessUnitCode": "NT"
      },
      "Actions": [
        {
          "Channel": "Email",
          "TemplateId": "P52CT9"
        }
      ]
    },
    {
      "BusinessDimensionValues": {
        "BusinessProviderCode": "DOLOREM_DELECTUS_",
        "BusinessUnitCode": "NT"
      },
      "Actions": [
        {
          "Channel": "Email",
          "TemplateId": "X1YR5W"
        }
      ]
    },
    {
      "BusinessDimensionValues": {
        "BusinessProviderCode": "SIMILIQUE_",
        "BusinessUnitCode": "NT"
      },
      "Actions": [
        {
          "Channel": "Email",
          "TemplateId": "F522JS"
        }
      ]
    },
    {
      "BusinessDimensionValues": {
        "BusinessProviderCode": "OCCAECATI",
        "BusinessUnitCode": "NT"
      },
      "Actions": [
        {
          "Channel": "Email",
          "TemplateId": "74R33D"
        }
      ]
    },
    {
      "BusinessDimensionValues": {
        "BusinessProviderCode": "CONSE",
        "BusinessUnitCode": "NT"
      },
      "Actions": [
        {
          "Channel": "Email",
          "TemplateId": "2ZXEI5"
        }
      ]
    },
    {
      "BusinessDimensionValues": {
        "BusinessProviderCode": "QUIA",
        "BusinessUnitCode": "NT"
      },
      "Actions": [
        {
          "Channel": "Email",
          "TemplateId": "20YX4L"
        }
      ]
    },
    {
      "BusinessDimensionValues": {
        "BusinessProviderCode": "VEL_LIBERO_",
        "BusinessUnitCode": "NT"
      },
      "Actions": [
        {
          "Channel": "Email",
          "TemplateId": "4MAD05"
        }
      ]
    },
    {
      "BusinessDimensionValues": {
        "BusinessProviderCode": "NISI_EA_EVEN",
        "BusinessUnitCode": "NT"
      },
      "Actions": [
        {
          "Channel": "Email",
          "TemplateId": "Y76JY5"
        }
      ]
    },
    {
      "BusinessDimensionValues": {
        "PartnerCode": "OFFIC",
        "BusinessUnitCode": "NT"
      },
      "Actions": [
        {
          "Channel": "Email",
          "TemplateId": "WX65RE"
        }
      ]
    },
    {
      "BusinessDimensionValues": {
        "BusinessProviderCode": "*",
        "BusinessUnitCode": "NT"
      },
      "Actions": []
    },
    {
      "BusinessDimensionValues": {
        "BusinessProviderCode": "OFFIC",
        "BusinessUnitCode": "HM"
      },
      "Actions": [
        {
          "Channel": "Email",
          "TemplateId": "XWLJBX"
        }
      ]
    },
    {
      "BusinessDimensionValues": {
        "BusinessProviderCode": "ET_ANIMI_IN_",
        "BusinessUnitCode": "HM"
      },
      "Actions": [
        {
          "Channel": "Email",
          "TemplateId": "0LUAZE"
        }
      ]
    },
    {
      "BusinessDimensionValues": {
        "BusinessProviderCode": "IPSUM_ALI",
        "BusinessUnitCode": "HM"
      },
      "Actions": [
        {
          "Channel": "Email",
          "TemplateId": "GLQOX8"
        }
      ]
    },
    {
      "BusinessDimensionValues": {
        "BusinessProviderCode": "REPREHENDERIT_Q",
        "BusinessUnitCode": "HM"
      },
      "Actions": [
        {
          "Channel": "Email",
          "TemplateId": "9T13KB"
        }
      ]
    },
    {
      "BusinessDimensionValues": {
        "BusinessProviderCode": "CONSEQUATUR_",
        "BusinessUnitCode": "HM"
      },
      "Actions": [
        {
          "Channel": "Email",
          "TemplateId": "XXQJH6"
        }
      ]
    },
    {
      "BusinessDimensionValues": {
        "BusinessProviderCode": "QUAERAT_N",
        "BusinessUnitCode": "HM"
      },
      "Actions": [
        {
          "Channel": "Email",
          "TemplateId": "EQTAEV"
        }
      ]
    },
    {
      "BusinessDimensionValues": {
        "BusinessProviderCode": "DISTINCTIO_DO",
        "BusinessUnitCode": "HM"
      },
      "Actions": [
        {
          "Channel": "Email",
          "TemplateId": "OQ2ZKL"
        }
      ]
    },
    {
      "BusinessDimensionValues": {
        "BusinessProviderCode": "PERSPICIAT",
        "BusinessUnitCode": "HM"
      },
      "Actions": [
        {
          "Channel": "Email",
          "TemplateId": "A5IFBM"
        }
      ]
    },
    {
      "BusinessDimensionValues": {
        "BusinessProviderCode": "ULLAM_HARUM_",
        "BusinessUnitCode": "HM"
      },
      "Actions": [
        {
          "Channel": "Email",
          "TemplateId": "HCI8TW"
        }
      ]
    },
    {
      "BusinessDimensionValues": {
        "BusinessProviderCode": "VOLUPTATI",
        "BusinessUnitCode": "HM"
      },
      "Actions": [
        {
          "Channel": "Email",
          "TemplateId": "MHQB59"
        }
      ]
    },
    {
      "BusinessDimensionValues": {
        "BusinessProviderCode": "PRAESENTIUM_NUL",
        "BusinessUnitCode": "HM"
      },
      "Actions": [
        {
          "Channel": "Email",
          "TemplateId": "UX1NPU"
        }
      ]
    },
    {
      "BusinessDimensionValues": {
        "BusinessProviderCode": "QUIDEM_EIUS_HIC_U",
        "BusinessUnitCode": "HM"
      },
      "Actions": [
        {
          "Channel": "Email",
          "TemplateId": "N1QBE3"
        }
      ]
    },
    {
      "BusinessDimensionValues": {
        "BusinessProviderCode": "MAIORES_QUIS_SOLUTA_",
        "BusinessUnitCode": "HM"
      },
      "Actions": [
        {
          "Channel": "Email",
          "TemplateId": "FN8AYJ"
        }
      ]
    },
    {
      "BusinessDimensionValues": {
        "BusinessProviderCode": "ET_EVENIET_HARUM_",
        "BusinessUnitCode": "HM"
      },
      "Actions": [
        {
          "Channel": "Email",
          "TemplateId": "EKWK1O"
        }
      ]
    },
    {
      "BusinessDimensionValues": {
        "BusinessProviderCode": "MAGNAM_SOLUT",
        "BusinessUnitCode": "HM"
      },
      "Actions": [
        {
          "Channel": "Email",
          "TemplateId": "ASVZHJ"
        }
      ]
    },
    {
      "BusinessDimensionValues": {
        "BusinessProviderCode": "DOLOR_DOL",
        "BusinessUnitCode": "HM"
      },
      "Actions": [
        {
          "Channel": "Email",
          "TemplateId": "WQ2YDA"
        }
      ]
    },
    {
      "BusinessDimensionValues": {
        "BusinessProviderCode": "QUAS_AUT",
        "BusinessUnitCode": "HM"
      },
      "Actions": [
        {
          "Channel": "Email",
          "TemplateId": "7VL0UG"
        }
      ]
    },
    {
      "BusinessDimensionValues": {
        "BusinessProviderCode": "NIHIL_EX_H",
        "BusinessUnitCode": "HM"
      },
      "Actions": [
        {
          "Channel": "Email",
          "TemplateId": "N4FQ5W"
        }
      ]
    },
    {
      "BusinessDimensionValues": {
        "BusinessProviderCode": "EX_VERITATIS_COR",
        "BusinessUnitCode": "HM"
      },
      "Actions": [
        {
          "Channel": "Email",
          "TemplateId": "EE1STU"
        }
      ]
    },
    {
      "BusinessDimensionValues": {
        "BusinessProviderCode": "BEATAE_LIBERO_OCCAE",
        "BusinessUnitCode": "HM"
      },
      "Actions": [
        {
          "Channel": "Email",
          "TemplateId": "C1YX4Y"
        }
      ]
    },
    {
      "BusinessDimensionValues": {
        "PartnerCode": "OFFIC",
        "BusinessUnitCode": "HM"
      },
      "Actions": [
        {
          "Channel": "Email",
          "TemplateId": "5FYECN"
        }
      ]
    },
    {
      "BusinessDimensionValues": {
        "BusinessProviderCode": "*",
        "BusinessUnitCode": "HM"
      },
      "Actions": []
    },
    {
      "BusinessDimensionValues": {
        "PartnerCode": "TEMPORIB",
        "ProductCode": "DOLOR_ANIMI_QU",
        "BusinessUnitCode": "EX"
      },
      "Actions": [
        {
          "Channel": "Email",
          "TemplateId": "IS2AKT"
        }
      ]
    },
    {
      "BusinessDimensionValues": {
        "PartnerCode": "TEMPORIB",
        "ProductCode": "PROVIDENT_MINIMA_",
        "BusinessUnitCode": "EX"
      },
      "Actions": [
        {
          "Channel": "Email",
          "TemplateId": "IAK9UC"
        }
      ]
    },
    {
      "BusinessDimensionValues": {
        "PartnerCode": "OFFIC",
        "ProductCode": "PROVIDENT_MINIMA_",
        "BusinessUnitCode": "EX"
      },
      "Actions": [
        {
          "Channel": "Email",
          "TemplateId": "KMLUQW"
        }
      ]
    }
  ]
}